perfunctory/__init__.py
perfunctory/rbaa.py
perfunctory-0.0.5.dist-info/LICENSE.txt
perfunctory-0.0.5.dist-info/METADATA
perfunctory-0.0.5.dist-info/WHEEL
perfunctory-0.0.5.dist-info/top_level.txt
perfunctory-0.0.5.dist-info/RECORD
